core/__init__.py
core/exceptions.py
settings/__init__.py
settings/settings.py
stock_time_series/__init__.py
stock_time_series/__main__.py
stock_time_series/stock_series.py
alphavantage_api_cesar-1.0.5.dist-info/METADATA
alphavantage_api_cesar-1.0.5.dist-info/WHEEL
alphavantage_api_cesar-1.0.5.dist-info/entry_points.txt
alphavantage_api_cesar-1.0.5.dist-info/top_level.txt
alphavantage_api_cesar-1.0.5.dist-info/RECORD
