Metadata-Version: 2.1
Name: alphavantage-api-cesar
Version: 1.0.5
Summary: Projeto desenvolvido para primeira semana do cesar inova afro bootcamp
Home-page: https://github.com/ekdespe/
Author: Erik Ferreira
Author-email: ekdespe@gmail.com
License: MIT
Platform: UNKNOWN
Classifier: License :: OSI Approved :: MIT License
Classifier: Programming Language :: Python :: 3
Classifier: Programming Language :: Python :: 3.7
Requires-Dist: python-decouple
Requires-Dist: requests
